forecast_tools/__init__.py
forecast_tools/baseline.py
forecast_tools/datasets.py
forecast_tools/feature_engineering.py
forecast_tools/metrics.py
forecast_tools/model_selection.py
forecast_tools/plotting.py
forecast_tools/data/ed_ts.csv
forecast_tools-0.4.1.dist-info/METADATA
forecast_tools-0.4.1.dist-info/WHEEL
forecast_tools-0.4.1.dist-info/licenses/LICENSE
forecast_tools-0.4.1.dist-info/RECORD
