Metadata-Version: 2.4
Name: forecast-tools
Version: 0.4.1
Summary: Tools to support forecasting education in Python
Project-URL: Homepage, https://github.com/TomMonks/forecast-tools
Project-URL: Bug Tracker, https://github.com/TomMonks/forecast-tools/issues
Project-URL: Documentation, https://tommonks.github.io/forecast-tools
Project-URL: Changelog, https://github.com/TomMonks/forecast-tools/blob/master/CHANGELOG.md
Author-email: Thomas Monks <forecast_tools@gmail.com>
License-Expression: MIT
License-File: LICENSE
Keywords: education,error-metrics,forecasting,naive,snaive,time-series
Classifier: License :: OSI Approved :: MIT License
Classifier: Operating System :: OS Independent
Classifier: Programming Language :: Python :: 3.9
Classifier: Programming Language :: Python :: 3.10
Classifier: Programming Language :: Python :: 3.11
Classifier: Programming Language :: Python :: 3.12
Requires-Python: >=3.9
Requires-Dist: joblib>=0.14.1
Requires-Dist: matplotlib>=3.1.3
Requires-Dist: numpy>=1.18.1
Requires-Dist: pandas>=1.0.1
Requires-Dist: plotly>6.0.0
Requires-Dist: scipy>=1.4.1
Requires-Dist: seaborn>=0.10.0
